httpcore/__init__.py
httpcore/_api.py
httpcore/_exceptions.py
httpcore/_models.py
httpcore/_ssl.py
httpcore/_synchronization.py
httpcore/_trace.py
httpcore/_utils.py
httpcore/py.typed
httpcore/_async/__init__.py
httpcore/_async/connection.py
httpcore/_async/connection_pool.py
httpcore/_async/http11.py
httpcore/_async/http2.py
httpcore/_async/http_proxy.py
httpcore/_async/interfaces.py
httpcore/_async/socks_proxy.py
httpcore/_sync/__init__.py
httpcore/_sync/connection.py
httpcore/_sync/connection_pool.py
httpcore/_sync/http11.py
httpcore/_sync/http2.py
httpcore/_sync/http_proxy.py
httpcore/_sync/interfaces.py
httpcore/_sync/socks_proxy.py
httpcore/backends/__init__.py
httpcore/backends/asyncio.py
httpcore/backends/auto.py
httpcore/backends/base.py
httpcore/backends/mock.py
httpcore/backends/sync.py
httpcore/backends/trio.py
httpcore-0.17.1.dist-info/LICENSE.md
httpcore-0.17.1.dist-info/METADATA
httpcore-0.17.1.dist-info/WHEEL
httpcore-0.17.1.dist-info/top_level.txt
httpcore-0.17.1.dist-info/RECORD
