Metadata-Version: 2.1
Name: httpcore
Version: 0.17.1
Summary: A minimal low-level HTTP client.
Home-page: https://github.com/encode/httpcore
Author: Tom Christie
Author-email: tom@tomchristie.com
License: BSD
Project-URL: Documentation, https://www.encode.io/httpcore
Project-URL: Source, https://github.com/encode/httpcore
Classifier: Development Status :: 3 - Alpha
Classifier: Environment :: Web Environment
Classifier: Intended Audience :: Developers
Classifier: License :: OSI Approved :: BSD License
Classifier: Operating System :: OS Independent
Classifier: Topic :: Internet :: WWW/HTTP
Classifier: Framework :: AsyncIO
Classifier: Framework :: Trio
Classifier: Programming Language :: Python :: 3
Classifier: Programming Language :: Python :: 3.7
Classifier: Programming Language :: Python :: 3.8
Classifier: Programming Language :: Python :: 3.9
Classifier: Programming Language :: Python :: 3.10
Classifier: Programming Language :: Python :: 3.11
Classifier: Programming Language :: Python :: 3 :: Only
Requires-Python: >=3.7
Provides-Extra: http2
Provides-Extra: socks
License-File: LICENSE.md
